README.rst
setup.py
MongoNotebookManager.egg-info/PKG-INFO
MongoNotebookManager.egg-info/SOURCES.txt
MongoNotebookManager.egg-info/dependency_links.txt
MongoNotebookManager.egg-info/entry_points.txt
MongoNotebookManager.egg-info/requires.txt
MongoNotebookManager.egg-info/top_level.txt
mongo_notebook_manager/__init__.py
mongo_notebook_manager/mongodb_proxy.py
mongo_notebook_manager/notebooks_importer.py