Metadata-Version: 1.1
Name: MongoNotebookManager
Version: 1.0.0
Summary: A notebook manager for IPython with MongoDB as the backend.
Home-page: https://github.com/laurenceputra/mongo_notebook_manager
Author: Laurence Putra
Author-email: laurenceputra@gmail.com
License: GPL v3
Keywords: mongo notebook manager ipython database storage
Platform: UNKNOWN
Classifier: Development Status :: 5 - Production/Stable
Classifier: Topic :: Database :: Front-Ends
Classifier: Framework :: IPython
Classifier: License :: OSI Approved :: GNU General Public License v3 (GPLv3)
Classifier: Intended Audience :: Developers
Classifier: Operating System :: OS Independent
